flyout_multiversion/__init__.py
flyout_multiversion/errors.py
flyout_multiversion/flyout_menu.py
flyout_multiversion/git.py
flyout_multiversion/_templates/versions.html
sphinx_flyout/__init__.py
sphinx_flyout/_templates/versions.html
sphinx_flyout-0.1.dist-info/METADATA
sphinx_flyout-0.1.dist-info/WHEEL
sphinx_flyout-0.1.dist-info/top_level.txt
sphinx_flyout-0.1.dist-info/RECORD
