Metadata-Version: 2.1
Name: sphinx-flyout
Version: 0.1
Summary: Расширение для Sphinx для создания flyout-меню
Author: IRS Ural
Project-URL: Homepage, https://github.com/irsural/sphinx-flyout
Classifier: Programming Language :: Python :: 3
Classifier: License :: OSI Approved :: MIT License
Classifier: Operating System :: OS Independent
Requires-Python: >=3.7
Requires-Dist: Sphinx
Requires-Dist: docutils
Requires-Dist: setuptools
Requires-Dist: sphinx-rtd-theme
Provides-Extra: dev
Requires-Dist: pytest ==7.4.4 ; extra == 'dev'
Requires-Dist: ruff ==0.4.9 ; extra == 'dev'
Requires-Dist: mypy ==1.4.1 ; extra == 'dev'
Requires-Dist: mypy-extensions ==1.0.0 ; extra == 'dev'
